{
  "order": 1,
  "name": "Shukhmani Gambhir",
  "social_media_handle": "Shukhmani Gambhir",
  "description": "I believe that fashion is a way to express yourself and have fun, so I'm not afraid to experiment with different trends and styles.",
  "total_followers": "644K Followers",
  "image_url": "/assets/images/Shukhmani-Gambhir/image1.svg",
  "accessories": [
    {
      "image_url": "/assets/images/Shukhmani-Gambhir/image2.svg",
      "hashtag": "#EthnicLuncheon",
      "is_dm": true,
      "buy_link": "",
      "price": 1200,
      "buy_tagline": "Buy The Sports Bra"
    },
    {
      "image_url": "/assets/images/Shukhmani-Gambhir/image3.svg",
      "hashtag": "#FloralFlush",
      "is_dm": true,
      "buy_link": "",
      "price": 1200,
      "buy_tagline": "Buy The Sports Bra"
    },
    {
      "image_url": "/assets/images/Shukhmani-Gambhir/image4.svg",
      "hashtag": "#FloralFlush",
      "is_dm": true,
      "buy_link": "",
      "price": 1200,
      "buy_tagline": "Buy The Sports Bra"
    },
    {
      "image_url": "/assets/images/Shukhmani-Gambhir/image5.svg",
      "hashtag": "#EthnicLuncheon",
      "is_dm": true,
      "buy_link": "",
      "price": 1200,
      "buy_tagline": "Buy The Sports Bra"
    },
    {
      "image_url": "/assets/images/Shukhmani-Gambhir/image6.svg",
      "hashtag": "#EthnicLuncheon",
      "is_dm": true,
      "buy_link": "",
      "price": 1200,
      "buy_tagline": "Buy The Sports Bra"
    },
    {
      "image_url": "/assets/images/Shukhmani-Gambhir/image7.svg",
      "hashtag": "#EthnicLuncheon",
      "is_dm": true,
      "buy_link": "",
      "price": 1200,
      "buy_tagline": "Buy The Sports Bra"
    },
    {
      "image_url": "/assets/images/Shukhmani-Gambhir/image8.svg",
      "hashtag": "#EthnicLuncheon",
      "is_dm": true,
      "buy_link": "",
      "price": 1200,
      "buy_tagline": "Buy The Sports Bra"
    }
  ]
}
